easy_formset/__init__.py
easy_formset/apps.py
easy_formset/forms.py
easy_formset/static/easy_formset/easy_formset.css
easy_formset/static/easy_formset/easy_formset.js
django_easy_formset-0.2.4.dist-info/METADATA
django_easy_formset-0.2.4.dist-info/WHEEL
django_easy_formset-0.2.4.dist-info/top_level.txt
django_easy_formset-0.2.4.dist-info/RECORD
